{
    "(('x', (29,), 1), ('x', (1,), 3))": "-567516950/81",
    "(('x', (28,), 1), ('x', (2,), 1), ('x', (1,), 2))": "-532532000/81",
    "(('x', (26,), 1), ('x', (4,), 1), ('x', (1,), 2))": "-547947400/81",
    "(('x', (25,), 1), ('x', (5,), 1), ('x', (1,), 2))": "-551551000/81",
    "(('x', (23,), 1), ('x', (7,), 1), ('x', (1,), 2))": "-60214000/9",
    "(('x', (22,), 1), ('x', (8,), 1), ('x', (1,), 2))": "-60860800/9",
    "(('x', (20,), 1), ('x', (10,), 1), ('x', (1,), 2))": "-182474600/27",
    "(('x', (19,), 1), ('x', (11,), 1), ('x', (1,), 2))": "-60860800/9",
    "(('x', (17,), 1), ('x', (13,), 1), ('x', (1,), 2))": "-182932750/27",
    "(('x', (16,), 1), ('x', (14,), 1), ('x', (1,), 2))": "-60860800/9",
    "(('x', (25,), 1), ('x', (4,), 1), ('x', (2,), 1), ('x', (1,), 1))": "-532532000/81",
    "(('x', (22,), 1), ('x', (7,), 1), ('x', (2,), 1), ('x', (1,), 1))": "-176496320/27",
    "(('x', (19,), 1), ('x', (10,), 1), ('x', (2,), 1), ('x', (1,), 1))": "-59477600/9",
    "(('x', (16,), 1), ('x', (13,), 1), ('x', (2,), 1), ('x', (1,), 1))": "-177923200/27",
    "(('x', (23,), 1), ('x', (4,), 2), ('x', (1,), 1))": "-168599200/27",
    "(('x', (22,), 1), ('x', (5,), 1), ('x', (4,), 1), ('x', (1,), 1))": "-170410240/27",
    "(('x', (20,), 1), ('x', (7,), 1), ('x', (4,), 1), ('x', (1,), 1))": "-168599200/27",
    "(('x', (19,), 1), ('x', (8,), 1), ('x', (4,), 1), ('x', (1,), 1))": "-170410240/27",
    "(('x', (17,), 1), ('x', (10,), 1), ('x', (4,), 1), ('x', (1,), 1))": "-171164840/27",
    "(('x', (16,), 1), ('x', (11,), 1), ('x', (4,), 1), ('x', (1,), 1))": "-170410240/27",
    "(('x', (14,), 1), ('x', (13,), 1), ('x', (4,), 1), ('x', (1,), 1))": "-170410240/27",
    "(('x', (19,), 1), ('x', (7,), 1), ('x', (5,), 1), ('x', (1,), 1))": "-170410240/27",
    "(('x', (16,), 1), ('x', (10,), 1), ('x', (5,), 1), ('x', (1,), 1))": "-172244800/27",
    "(('x', (13,), 2), ('x', (5,), 1), ('x', (1,), 1))": "-171830750/27",
    "(('x', (17,), 1), ('x', (7,), 2), ('x', (1,), 1))": "-56444080/9",
    "(('x', (16,), 1), ('x', (8,), 1), ('x', (7,), 1), ('x', (1,), 1))": "-170410240/27",
    "(('x', (14,), 1), ('x', (10,), 1), ('x', (7,), 1), ('x', (1,), 1))": "-170841440/27",
    "(('x', (13,), 1), ('x', (11,), 1), ('x', (7,), 1), ('x', (1,), 1))": "-170410240/27",
    "(('x', (13,), 1), ('x', (10,), 1), ('x', (8,), 1), ('x', (1,), 1))": "-172244800/27",
    "(('x', (11,), 1), ('x', (10,), 2), ('x', (1,), 1))": "-19188400/3",
    "(('x', (26,), 1), ('x', (2,), 3))": "626225600/81",
    "(('x', (23,), 1), ('x', (5,), 1), ('x', (2,), 2))": "186663400/27",
    "(('x', (20,), 1), ('x', (8,), 1), ('x', (2,), 2))": "190590400/27",
    "(('x', (17,), 1), ('x', (11,), 1), ('x', (2,), 2))": "63355600/9",
    "(('x', (14,), 2), ('x', (2,), 2))": "189728000/27",
    "(('x', (22,), 1), ('x', (4,), 2), ('x', (2,), 1))": "-170410240/27",
    "(('x', (19,), 1), ('x', (7,), 1), ('x', (4,), 1), ('x', (2,), 1))": "-170410240/27",
    "(('x', (16,), 1), ('x', (10,), 1), ('x', (4,), 1), ('x', (2,), 1))": "-173264000/27",
    "(('x', (13,), 2), ('x', (4,), 1), ('x', (2,), 1))": "-170588600/27",
    "(('x', (20,), 1), ('x', (5,), 2), ('x', (2,), 1))": "166243000/27",
    "(('x', (17,), 1), ('x', (8,), 1), ('x', (5,), 1), ('x', (2,), 1))": "170693600/27",
    "(('x', (14,), 1), ('x', (11,), 1), ('x', (5,), 1), ('x', (2,), 1))": "169400000/27",
    "(('x', (16,), 1), ('x', (7,), 2), ('x', (2,), 1))": "-57075200/9",
    "(('x', (13,), 1), ('x', (10,), 1), ('x', (7,), 1), ('x', (2,), 1))": "-172117400/27",
    "(('x', (14,), 1), ('x', (8,), 2), ('x', (2,), 1))": "58150400/9",
    "(('x', (11,), 2), ('x', (8,), 1), ('x', (2,), 1))": "173465600/27",
    "(('x', (10,), 3), ('x', (2,), 1))": "-175616000/27",
    "(('x', (20,), 1), ('x', (4,), 3))": "-146608000/27",
    "(('x', (19,), 1), ('x', (5,), 1), ('x', (4,), 2))": "-147172480/27",
    "(('x', (17,), 1), ('x', (7,), 1), ('x', (4,), 2))": "-151006240/27",
    "(('x', (16,), 1), ('x', (8,), 1), ('x', (4,), 2))": "-153287680/27",
    "(('x', (14,), 1), ('x', (10,), 1), ('x', (4,), 2))": "-152817280/27",
    "(('x', (13,), 1), ('x', (11,), 1), ('x', (4,), 2))": "-150230080/27",
    "(('x', (16,), 1), ('x', (7,), 1), ('x', (5,), 1), ('x', (4,), 1))": "-152064640/27",
    "(('x', (13,), 1), ('x', (10,), 1), ('x', (5,), 1), ('x', (4,), 1))": "-152243000/27",
    "(('x', (14,), 1), ('x', (7,), 2), ('x', (4,), 1))": "-154542080/27",
    "(('x', (13,), 1), ('x', (8,), 1), ('x', (7,), 1), ('x', (4,), 1))": "-155122240/27",
    "(('x', (11,), 1), ('x', (10,), 1), ('x', (7,), 1), ('x', (4,), 1))": "-154887040/27",
    "(('x', (10,), 2), ('x', (8,), 1), ('x', (4,), 1))": "-157976000/27",
    "(('x', (17,), 1), ('x', (5,), 3))": "151516750/27",
    "(('x', (14,), 1), ('x', (8,), 1), ('x', (5,), 2))": "154616000/27",
    "(('x', (11,), 2), ('x', (5,), 2))": "151976000/27",
    "(('x', (13,), 1), ('x', (7,), 2), ('x', (5,), 1))": "-51724400/9",
    "(('x', (10,), 2), ('x', (7,), 1), ('x', (5,), 1))": "-156065000/27",
    "(('x', (11,), 1), ('x', (8,), 2), ('x', (5,), 1))": "156640000/27",
    "(('x', (11,), 1), ('x', (7,), 3))": "-156956800/27",
    "(('x', (10,), 1), ('x', (8,), 1), ('x', (7,), 2))": "-17561600/3",
    "(('x', (8,), 4),)": "160000000/27"
}